tgboost/VERSION
tgboost/__init__.py
tgboost/config.yml
tgboost/predict.py
tgboost/regressor.py
tgboost/train_pipeline.py
tgboost/transformer.py
tgboost/config/__init__.py
tgboost/config/core.py
tgboost/datasets/BradleyDoublePlusGoodMeltingPointDataset_Highly_Curated_and_Validated.xlsx
tgboost/datasets/Koop_dataset.csv
tgboost/datasets/Koop_dataset_Rothfuss_t0_bis.csv
tgboost/datasets/__init__.py
tgboost/datasets/test.csv
tgboost/datasets/train.csv
tgboost/processing/__init__.py
tgboost/processing/data_manager.py
tgboost/processing/smiles_manager.py
tgboost/processing/validation.py
tgboost/trained_models/__init__.py
tgboost/trained_models/model_300dim.pkl
tgboost/trained_models/tgModel_output_v0.0.6.pkl
tgboost/trained_models/tgModel_transformer_pipe_v0.0.6.pkl
tgapp-0.0.6.dist-info/LICENSE.txt
tgapp-0.0.6.dist-info/METADATA
tgapp-0.0.6.dist-info/WHEEL
tgapp-0.0.6.dist-info/top_level.txt
tgapp-0.0.6.dist-info/RECORD
