Metadata-Version: 2.1
Name: tgapp
Version: 0.0.6
Summary: Package for prediction of chemical species properties from SMILES.
Home-page: https://github.com/U0M0Z/tgboost
Author: Tommaso Galeazzo | www.tmsglz.com
Author-email: tommaso.galeazzo@gmail.com
License: BSD-3
Platform: UNKNOWN
Classifier: License :: OSI Approved :: MIT License
Classifier: Programming Language :: Python
Classifier: Programming Language :: Python :: 3
Classifier: Programming Language :: Python :: 3.6
Classifier: Programming Language :: Python :: 3.7
Classifier: Programming Language :: Python :: 3.8
Classifier: Programming Language :: Python :: 3.9
Classifier: Programming Language :: Python :: Implementation :: CPython
Classifier: Programming Language :: Python :: Implementation :: PyPy
Requires-Python: >=3.6.0
License-File: LICENSE.txt
Requires-Dist: numpy (<1.21.0,>=1.20.0)
Requires-Dist: pandas (<1.3.0,>=1.2.0)
Requires-Dist: pydantic (<2.0,>=1.10.5)
Requires-Dist: scikit-learn (<=0.24.2)
Requires-Dist: strictyaml (<1.4.0,>=1.3.2)
Requires-Dist: ruamel.yaml (==0.16.12)
Requires-Dist: feature-engine (<1.1.0,>=1.0.2)
Requires-Dist: joblib (<1.1.0,>=1.0.1)
Requires-Dist: xgboost (<=1.4.0)
Requires-Dist: gensim (==3.8.3)
Requires-Dist: rdkit-pypi
Requires-Dist: setuptools (<60.0.0)
